teable/__init__.py
teable/core/__init__.py
teable/core/access_tokens.py
teable/core/admin.py
teable/core/aggregation.py
teable/core/ai.py
teable/core/attachments.py
teable/core/auth.py
teable/core/billing.py
teable/core/cache.py
teable/core/client.py
teable/core/comments.py
teable/core/dashboard.py
teable/core/exports.py
teable/core/fields.py
teable/core/http.py
teable/core/imports.py
teable/core/integrity.py
teable/core/notifications.py
teable/core/oauth.py
teable/core/organizations.py
teable/core/pins.py
teable/core/plugins.py
teable/core/rate_limit.py
teable/core/records.py
teable/core/selection.py
teable/core/spaces.py
teable/core/tables.py
teable/core/undo_redo.py
teable/core/usage.py
teable/core/views.py
teable/exceptions/__init__.py
teable/models/__init__.py
teable/models/aggregation.py
teable/models/base.py
teable/models/collaborator.py
teable/models/config.py
teable/models/dashboard.py
teable/models/dashboard_plugin.py
teable/models/field.py
teable/models/history.py
teable/models/invitation.py
teable/models/permission.py
teable/models/plugin.py
teable/models/record.py
teable/models/selection.py
teable/models/space.py
teable/models/table.py
teable/models/trash.py
teable/models/user.py
teable/models/view.py
teable/models/view_plugin.py
teable_client-1.2.2.dist-info/licenses/LICENSE
tests/__init__.py
tests/conftest.py
tests/test_auth.py
tests/test_auth_unit.py
tests/test_base.py
tests/test_client.py
tests/test_debug.py
tests/test_field_view_unit.py
tests/test_real_auth.py
tests/test_real_space_base.py
tests/test_real_table.py
tests/test_real_view.py
tests/test_record.py
tests/test_simple.py
tests/test_space.py
tests/test_space_base_ops_unit.py
tests/test_space_unit.py
tests/test_table.py
tests/test_view.py
tests/utils.py
teable_client-1.2.2.dist-info/METADATA
teable_client-1.2.2.dist-info/WHEEL
teable_client-1.2.2.dist-info/top_level.txt
teable_client-1.2.2.dist-info/RECORD
